pytorch_lightning_help/__init__.py
pytorch_lightning_help/callbacks.py
pytorch_lightning_help/version.py
tests/__init__.py
tests/test_example.py
pytorch_lightning_help-0.0.1.dist-info/LICENSE
pytorch_lightning_help-0.0.1.dist-info/METADATA
pytorch_lightning_help-0.0.1.dist-info/WHEEL
pytorch_lightning_help-0.0.1.dist-info/top_level.txt
pytorch_lightning_help-0.0.1.dist-info/RECORD
