Metadata-Version: 2.1
Name: pytorch-lightning-help
Version: 0.0.1
Summary: Pytorch lightning help
Home-page: https://github.com/genggui001/pytorch_lightning_help
Author: genggui001
Author-email: genggui001@gmail.com
License: UNKNOWN
Platform: UNKNOWN
Classifier: Programming Language :: Python :: 3
Classifier: License :: OSI Approved :: MIT License
Classifier: Operating System :: OS Independent
Requires-Dist: pytorch-lightning (==1.0.5)
